ambient_client_common/__init__.py
ambient_client_common/config.py
ambient_client_common/main.py
ambient_client_common/models/__init__.py
ambient_client_common/models/cluster_diff.py
ambient_client_common/models/docker_models.py
ambient_client_common/repositories/__init__.py
ambient_client_common/repositories/backend_api_repo.py
ambient_client_common/repositories/base_api_repo.py
ambient_client_common/repositories/docker_repo.py
ambient_client_common/repositories/local_api_repo.py
ambient_client_common/services/__init__.py
ambient_client_common/utils/__init__.py
ambient_client_common/utils/consistent_hash.py
ambient_client_common/utils/custom_logger.py
ambient_client_common-1.8.0.dist-info/METADATA
ambient_client_common-1.8.0.dist-info/WHEEL
ambient_client_common-1.8.0.dist-info/top_level.txt
ambient_client_common-1.8.0.dist-info/RECORD
