Metadata-Version: 2.4
Name: ambient_client_common
Version: 1.8.0
Summary: Common libraries all edge client packages
Author-email: Jose Catarino <jose@ambientlabscomputing.com>
License: MIT
Requires-Python: >=3.7
Requires-Dist: pydantic<=2.7.4
Requires-Dist: ambient_backend_api_client>=3.0.1
